CatsAss-1.1.3.dist-info/DESCRIPTION.rst
CatsAss-1.1.3.dist-info/METADATA
CatsAss-1.1.3.dist-info/RECORD
CatsAss-1.1.3.dist-info/WHEEL
CatsAss-1.1.3.dist-info/metadata.json
CatsAss-1.1.3.dist-info/top_level.txt
catsass/__init__.py
catsass/catsass.py
catsass/colorz.py
catsass/logo
catsass/octocat
catsass/test_catsass.py
