Metadata-Version: 2.0
Name: CatsAss
Version: 1.1.3
Summary: Seriously the cats ass. Seriously.
Home-page: https://github.com/Duroktar/CatsAss
Author: Duroktar
Author-email: duroktar@gmail.com
License: MIT
Platform: UNKNOWN
Classifier: Development Status :: 4 - Beta
Classifier: Intended Audience :: Developers
Classifier: Topic :: Software Development
Classifier: Topic :: Software Development :: Debuggers
Classifier: Topic :: Games/Entertainment :: Fortune Cookies
Classifier: License :: OSI Approved :: MIT License
Classifier: Programming Language :: Python :: 3
Classifier: Programming Language :: Python :: 3.6
